{".class":"MypyFile","_fullname":"rapps_sdk.errors","future_import_flags":[],"is_partial_stub_package":false,"is_stub":false,"names":{".class":"SymbolTable","APIError":{".class":"SymbolTableNode","kind":"Gdef","node":{".class":"TypeInfo","_promote":[],"abstract_attributes":[],"alt_promote":null,"bases":["rapps_sdk.errors.SDKError"],"dataclass_transform_spec":null,"declared_metaclass":null,"defn":{".class":"ClassDef","fullname":"rapps_sdk.errors.APIError","name":"APIError","type_vars":[]},"deletable_attributes":[],"deprecated":null,"flags":[],"fullname":"rapps_sdk.errors.APIError","has_param_spec_type":false,"metaclass_type":null,"metadata":{},"module_name":"rapps_sdk.errors","mro":["rapps_sdk.errors.APIError","rapps_sdk.errors.SDKError","builtins.Exception","builtins.BaseException","builtins.object"],"names":{".class":"SymbolTable","__init__":{".class":"SymbolTableNode","kind":"Mdef","node":{".class":"FuncDef","abstract_status":0,"arg_kinds":[0,0,0,0,3],"arg_names":["self","status","code","message","request_id"],"dataclass_transform_spec":null,"deprecated":null,"flags":["is_trivial_self"],"fullname":"rapps_sdk.errors.APIError.__init__","name":"__init__","original_first_arg":"self","type":{".class":"CallableType","arg_kinds":[0,0,0,0,3],"arg_names":["self","status","code","message","request_id"],"arg_types":["rapps_sdk.errors.APIError","builtins.int",{".class":"UnionType","items":["builtins.str",{".class":"NoneType"}],"uses_pep604_syntax":true},"builtins.str",{".class":"UnionType","items":["builtins.str",{".class":"NoneType"}],"uses_pep604_syntax":true}],"fallback":"builtins.function","from_concatenate":false,"implicit":false,"imprecise_arg_kinds":false,"is_bound":false,"is_ellipsis_args":false,"name":"__init__ of APIError","ret_type":{".class":"NoneType"},"type_guard":null,"type_is":null,"unpack_kwargs":false,"variables":[]}}},"code":{".class":"SymbolTableNode","implicit":true,"kind":"Mdef","node":{".class":"Var","flags":["is_ready","is_inferred"],"fullname":"rapps_sdk.errors.APIError.code","name":"code","setter_type":null,"type":{".class":"UnionType","items":["builtins.str",{".class":"NoneType"}],"uses_pep604_syntax":true}}},"message":{".class":"SymbolTableNode","implicit":true,"kind":"Mdef","node":{".class":"Var","flags":["is_ready","is_inferred"],"fullname":"rapps_sdk.errors.APIError.message","name":"message","setter_type":null,"type":"builtins.str"}},"request_id":{".class":"SymbolTableNode","implicit":true,"kind":"Mdef","node":{".class":"Var","flags":["is_ready","is_inferred"],"fullname":"rapps_sdk.errors.APIError.request_id","name":"request_id","setter_type":null,"type":{".class":"UnionType","items":["builtins.str",{".class":"NoneType"}],"uses_pep604_syntax":true}}},"status":{".class":"SymbolTableNode","implicit":true,"kind":"Mdef","node":{".class":"Var","flags":["is_ready","is_inferred"],"fullname":"rapps_sdk.errors.APIError.status","name":"status","setter_type":null,"type":"builtins.int"}}},"self_type":{".class":"TypeVarType","default":{".class":"AnyType","missing_import_name":null,"source_any":null,"type_of_any":4},"fullname":"rapps_sdk.errors.APIError.Self","id":0,"name":"Self","namespace":"","upper_bound":"rapps_sdk.errors.APIError","values":[],"variance":0},"slots":null,"tuple_type":null,"type_vars":[],"typeddict_type":null}},"AuthError":{".class":"SymbolTableNode","kind":"Gdef","node":{".class":"TypeInfo","_promote":[],"abstract_attributes":[],"alt_promote":null,"bases":["rapps_sdk.errors.APIError"],"dataclass_transform_spec":null,"declared_metaclass":null,"defn":{".class":"ClassDef","fullname":"rapps_sdk.errors.AuthError","name":"AuthError","type_vars":[]},"deletable_attributes":[],"deprecated":null,"flags":[],"fullname":"rapps_sdk.errors.AuthError","has_param_spec_type":false,"metaclass_type":null,"metadata":{},"module_name":"rapps_sdk.errors","mro":["rapps_sdk.errors.AuthError","rapps_sdk.errors.APIError","rapps_sdk.errors.SDKError","builtins.Exception","builtins.BaseException","builtins.object"],"names":{".class":"SymbolTable"},"self_type":{".class":"TypeVarType","default":{".class":"AnyType","missing_import_name":null,"source_any":null,"type_of_any":4},"fullname":"rapps_sdk.errors.AuthError.Self","id":0,"name":"Self","namespace":"","upper_bound":"rapps_sdk.errors.AuthError","values":[],"variance":0},"slots":null,"tuple_type":null,"type_vars":[],"typeddict_type":null}},"RateLimitError":{".class":"SymbolTableNode","kind":"Gdef","node":{".class":"TypeInfo","_promote":[],"abstract_attributes":[],"alt_promote":null,"bases":["rapps_sdk.errors.APIError"],"dataclass_transform_spec":null,"declared_metaclass":null,"defn":{".class":"ClassDef","fullname":"rapps_sdk.errors.RateLimitError","name":"RateLimitError","type_vars":[]},"deletable_attributes":[],"deprecated":null,"flags":[],"fullname":"rapps_sdk.errors.RateLimitError","has_param_spec_type":false,"metaclass_type":null,"metadata":{},"module_name":"rapps_sdk.errors","mro":["rapps_sdk.errors.RateLimitError","rapps_sdk.errors.APIError","rapps_sdk.errors.SDKError","builtins.Exception","builtins.BaseException","builtins.object"],"names":{".class":"SymbolTable"},"self_type":{".class":"TypeVarType","default":{".class":"AnyType","missing_import_name":null,"source_any":null,"type_of_any":4},"fullname":"rapps_sdk.errors.RateLimitError.Self","id":0,"name":"Self","namespace":"","upper_bound":"rapps_sdk.errors.RateLimitError","values":[],"variance":0},"slots":null,"tuple_type":null,"type_vars":[],"typeddict_type":null}},"SDKError":{".class":"SymbolTableNode","kind":"Gdef","node":{".class":"TypeInfo","_promote":[],"abstract_attributes":[],"alt_promote":null,"bases":["builtins.Exception"],"dataclass_transform_spec":null,"declared_metaclass":null,"defn":{".class":"ClassDef","fullname":"rapps_sdk.errors.SDKError","name":"SDKError","type_vars":[]},"deletable_attributes":[],"deprecated":null,"flags":[],"fullname":"rapps_sdk.errors.SDKError","has_param_spec_type":false,"metaclass_type":null,"metadata":{},"module_name":"rapps_sdk.errors","mro":["rapps_sdk.errors.SDKError","builtins.Exception","builtins.BaseException","builtins.object"],"names":{".class":"SymbolTable"},"self_type":{".class":"TypeVarType","default":{".class":"AnyType","missing_import_name":null,"source_any":null,"type_of_any":4},"fullname":"rapps_sdk.errors.SDKError.Self","id":0,"name":"Self","namespace":"","upper_bound":"rapps_sdk.errors.SDKError","values":[],"variance":0},"slots":null,"tuple_type":null,"type_vars":[],"typeddict_type":null}},"__annotations__":{".class":"SymbolTableNode","kind":"Gdef","node":{".class":"Var","flags":["is_ready"],"fullname":"rapps_sdk.errors.__annotations__","name":"__annotations__","setter_type":null,"type":{".class":"Instance","args":["builtins.str",{".class":"AnyType","missing_import_name":null,"source_any":null,"type_of_any":6}],"extra_attrs":null,"type_ref":"builtins.dict"}}},"__doc__":{".class":"SymbolTableNode","kind":"Gdef","node":{".class":"Var","flags":["is_ready"],"fullname":"rapps_sdk.errors.__doc__","name":"__doc__","setter_type":null,"type":"builtins.str"}},"__file__":{".class":"SymbolTableNode","kind":"Gdef","node":{".class":"Var","flags":["is_ready"],"fullname":"rapps_sdk.errors.__file__","name":"__file__","setter_type":null,"type":"builtins.str"}},"__name__":{".class":"SymbolTableNode","kind":"Gdef","node":{".class":"Var","flags":["is_ready"],"fullname":"rapps_sdk.errors.__name__","name":"__name__","setter_type":null,"type":"builtins.str"}},"__package__":{".class":"SymbolTableNode","kind":"Gdef","node":{".class":"Var","flags":["is_ready"],"fullname":"rapps_sdk.errors.__package__","name":"__package__","setter_type":null,"type":"builtins.str"}},"__spec__":{".class":"SymbolTableNode","kind":"Gdef","node":{".class":"Var","flags":["is_ready"],"fullname":"rapps_sdk.errors.__spec__","name":"__spec__","setter_type":null,"type":"_frozen_importlib.ModuleSpec"}}},"path":"src\\rapps_sdk\\errors.py"}